pyspherical/__init__.py
pyspherical/_temp.py
pyspherical/exp_sum_stability.py
pyspherical/making_inverse.py
pyspherical/test.py
pyspherical/test2.py
pyspherical/transforms.py
pyspherical/utils.py
pyspherical/wigner.py
pyspherical/tests/test_numba_funcs.py
pyspherical/tests/test_transforms.py
pyspherical/tests/test_utils.py
pyspherical/tests/test_wigner.py
pyspherical-0.0.2.dist-info/LICENSE
pyspherical-0.0.2.dist-info/METADATA
pyspherical-0.0.2.dist-info/WHEEL
pyspherical-0.0.2.dist-info/top_level.txt
pyspherical-0.0.2.dist-info/RECORD
