Metadata-Version: 2.1
Name: pyspherical
Version: 0.0.2
Summary: UNKNOWN
Home-page: https://github.com/aelanman/pyspherical
Author: Adam E. Lanman
License: MIT
Download-URL: https://github.com/aelanman/pyspherical/archive/v0.0.1.tar.gz
Keywords: spin spherical harmonic transforms wigner
Platform: UNKNOWN
Classifier: Development Status :: 3 - Alpha
Classifier: Intended Audience :: Science/Research
Classifier: License :: OSI Approved :: MIT License
Classifier: Programming Language :: Python :: 3.6
Classifier: Topic :: Scientific/Engineering :: Physics
Requires-Dist: numpy
Requires-Dist: numba
Requires-Dist: scipy
